dbt_databricks_factory/__init__.py
dbt_databricks_factory/builder.py
dbt_databricks_factory/cli.py
dbt_databricks_factory/config.py
dbt_databricks_factory-0.1.1.dist-info/LICENSE
dbt_databricks_factory-0.1.1.dist-info/METADATA
dbt_databricks_factory-0.1.1.dist-info/WHEEL
dbt_databricks_factory-0.1.1.dist-info/top_level.txt
dbt_databricks_factory-0.1.1.dist-info/RECORD
